Workbook

Sheet Guide
B2: OpenTrace Africa | Commodity Pricing Sources Tracker
B3: Research owner: Daniel. Candidate source leads are recorded; source-level verification is still required.
B5: How to use this tracker
B6: Pricing Tracker tab | C6: Each country has 5 rows, ranked 1 to 5. Rank 1 is the strongest pricing source for that country (most current, widest coverage, easiest to access).
B7: What to fill in | C7: Region, Country and Priority Rank are pre-filled. Researchers fill every column from Organisation to Notes. Cells with a dropdown only accept the listed values.
B8: Website | C8: Paste the direct link to the pricing page or data portal, not the organisation's homepage.
B9: Last Checked | C9: Enter the date you last confirmed the source is live and the frequency is correct (format YYYY-MM-DD).
B10: Fewer than 5 sources | C10: If a country genuinely has fewer than 5 sources, leave the extra rows blank and say why in Notes on the Rank 1 row.
B11: Summary tab | C11: Calculates automatically. Do not type in it. It shows, per country and per region, how many sources are found, have an API, are accessed or downloaded, and are ingested.
B12: Lists tab | C12: Holds the dropdown values. Edit there if a category needs adding.
B14: Status definitions
B15: Access Possibility | C15: Open: no login. Free registration: account needed, no cost. Paid: subscription or licence. Partnership needed: requires an agreement or MoU. Not accessible: exists but cannot be reached.
B16: Access Status | C16: Not started: identified only. Accessed: we have reached the data and confirmed it. Downloaded: we hold a copy or have pulled a sample.
B17: Ingestion Status | C17: Not ingested: not in the OpenTrace pipeline. In progress: handed to data engineering. Ingested: live in the pipeline and feeding Ask ADZA.
B18: Data Type | C18: Live: updated in real time. 24-hr delayed: daily refresh. Periodic: weekly, monthly or less. Historical only: no current updates.
B20: Example row (format guide only, verify before use)
B21: Region | C21: East Africa
B22: Country | C22: Kenya
B23: Priority Rank | C23: 1
B24: Organisation | C24: Kenya Agricultural Market Information System (KAMIS), Ministry of Agriculture
B25: Organisation Type | C25: Market Information System
B26: Website | C26: https://kamis.kilimo.go.ke
B27: Data Type | C27: 24-hr delayed
B28: Commodities Covered | C28: Maize, beans, potatoes, vegetables, livestock
B29: Geographic Level | C29: Market-level
B30: Update Frequency | C30: Daily
B31: API Available | C31: Unknown
B32: Access Possibility | C32: Open
B33: Access Status | C33: Accessed
B34: Ingestion Status | C34: Not ingested
B35: Last Checked | C35: 2026-10-18
... B43: Last checked | C43: Leave blank until that exact source row is checked. Dates are not backfilled from a general portal review.

Sheet Pricing Tracker
A1: Commodity Pricing Sources Tracker | 54 countries × top 5 sources
A2: All 54 countries populated with five candidate sources each. Verify direct pricing endpoints, coverage, access, API and freshness before ingestion.
A4: Region | B4: Country | C4: Priority Rank | D4: Organisation | E4: Organisation Type | F4: Website | G4: Data Type | H4: Commodities Covered | I4: Geographic Level | J4: Update Frequency | K4: API Available | L4: Access Possibility | M4: Access Status | N4: Ingestion Status | O4: Last Checked | P4: Researcher | Q4: Notes | R4: Verification Evidence | S4: Evidence Status | T4: Workstream
A5: North Africa | B5: Algeria | C5: 1 | D5: Algeria National Food Market / Price Reporting Source | E5: Market Information System | F5: https://www.fao.org/giews/food-prices/tool/public/#/home | G5: Periodic | H5: Staple grains, cereals and selected food commodities | I5: Market-level | J5: Periodic | K5: Unknown | L5: Open | M5: Not started | N5: Not ingested | P5: Daniel | Q5: Use FAO FPMA to check country/market coverage; this is not proof of a national live feed. | R5: Candidate lead from existing tracker; country/commodity coverage, latest observation, direct data endpoint and access method still require source-level verification. | S5: Candidate - not independently verified | T5: OpenTrace Africa
A6: North Africa | B6: Algeria | C6: 2 | D6: Office National des Statistiques (ONS) | E6: Statistics Office | F6: https://www.ons.dz | G6: Historical only | H6: Consumer food prices, CPI and food price indices | I6: National | J6: Monthly | K6: Unknown | L6: Open | M6: Not started | N6: Not ingested | P6: Daniel | Q6: Official institution landing page; locate a direct price table and confirm commodity-level data. | R6: Candidate lead from existing tracker; country/commodity coverage, latest observation, direct data endpoint and access method still require source-level verification. | S6: Candidate - not independently verified | T6: OpenTrace Africa
A7: North Africa | B7: Algeria | C7: 3 | D7: Ministry of Agriculture and Rural Development | E7: Government / Ministry | F7: https://madr.gov.dz | G7: Periodic | H7: Agricultural commodities, crops and market information where published | I7: National | J7: Periodic | K7: Unknown | L7: Open | M7: Not started | N7: Not ingested | P7: Daniel | Q7: Official institution landing page; commodity price series and publication frequency need verification. Candidate only; verify direct dataset, country/commodity coverage and access before ingestion. | R7: Candidate lead from existing tracker; country/commodity coverage, latest observation, direct data endpoint and access method still require source-level verification. | S7: Candidate - not independently verified | T7: OpenTrace Africa
A8: North Africa | B8: Algeria | C8: 4 | D8: FAO GIEWS Food Price Monitoring and Analysis (FPMA) | E8: Multilateral / UN | F8: https://www.fao.org/giews/food-prices/tool/public/#/home | G8: Periodic | H8: Domestic staple food prices and market series where available | I8: National / market-level | J8: Periodic | K8: Unknown | L8: Open | M8: Not started | N8: Not ingested | P8: Daniel | Q8: Search by country and commodity; confirm latest observation and download/API options. | R8: Candidate lead from existing tracker; country/commodity coverage, latest observation, direct data endpoint and access method still require source-level verification. | S8: Candidate - not independently verified | T8: OpenTrace Africa
A9: North Africa | B9: Algeria | C9: 5 | D9: WFP / HDX Food Prices Dataset | E9: Multilateral / UN | F9: https://data.humdata.org/dataset/wfp-food-prices | G9: Periodic | H9: Staple food prices in markets where WFP reporting exists | I9: Market-level | J9: Periodic | K9: Unknown | L9: Open | M9: Not started | N9: Not ingested | P9: Daniel | Q9: Cross-country dataset; confirm records for this country, dates, units and commodity coverage. | R9: Candidate lead from existing tracker; country/commodity coverage, latest observation, direct data endpoint and access method still require source-level verification. | S9: Candidate - not independently verified | T9: OpenTrace Africa
A10: North Africa | B10: Egypt | C10: 1 | D10: Egypt National Food Market / Price Reporting Source | E10: Market Information System | F10: https://www.fao.org/giews/food-prices/tool/public/#/home | G10: Periodic | H10: Staple grains, cereals and selected food commodities | I10: Market-level | J10: Periodic | K10: Unknown | L10: Open | M10: Not started | N10: Not ingested | P10: Daniel | Q10: Use FAO FPMA to check country/market coverage; this is not proof of a national live feed. | R10: Candidate lead from existing tracker; country/commodity coverage, latest observation, direct data endpoint and access method still require source-level verification. | S10: Candidate - not independently verified | T10: OpenTrace Africa
A11: North Africa | B11: Egypt | C11: 2 | D11: Central Agency for Public Mobilization and Statistics (CAPMAS) | E11: Statistics Office | F11: https://www.capmas.gov.eg | G11: Historical only | H11: Consumer food prices, CPI and food price indices | I11: National | J11: Monthly | K11: Unknown | L11: Open | M11: Not started | N11: Not ingested | P11: Daniel | Q11: Official institution landing page; locate a direct price table and confirm commodity-level data. | R11: Candidate lead from existing tracker; country/commodity coverage, latest observation, direct data endpoint and access method still require source-level verification. | S11: Candidate - not independently verified | T11: OpenTrace Africa
A12: North Africa | B12: Egypt | C12: 3 | D12: Ministry of Agriculture and Land Reclamation | E12: Government / Ministry | F12: https://moa.gov.eg | G12: Periodic | H12: Agricultural commodities, crops and market information where published | I12: National | J12: Periodic | K12: Unknown | L12: Open | M12: Not started | N12: Not ingested | P12: Daniel | Q12: Official institution landing page; commodity price series and publication frequency need verification. Candidate only; verify direct dataset, country/commodity coverage and access before ingestion. | R12: Candidate lead from existing tracker; country/commodity coverage, latest observation, direct data endpoint and access method still require source-level verification. | S12: Candidate - not independently verified | T12: OpenTrace Africa
A13: North Africa | B13: Egypt | C13: 4 | D13: FAO GIEWS Food Price Monitoring and Analysis (FPMA) | E13: Multilateral / UN | F13: https://www.fao.org/giews/food-prices/tool/public/#/home | G13: Periodic | H13: Domestic staple food prices and market series where available | I13: National / market-level | J13: Periodic | K13: Unknown | L13: Open | M13: Not started | N13: Not ingested | P13: Daniel | Q13: Search by country and commodity; confirm latest observation and download/API options. | R13: Candidate lead from existing tracker; country/commodity coverage, latest observation, direct data endpoint and access method still require source-level verification. | S13: Candidate - not independently verified | T13: OpenTrace Africa
A14: North Africa | B14: Egypt | C14: 5 | D14: WFP / HDX Food Prices Dataset | E14: Multilateral / UN | F14: https://data.humdata.org/dataset/wfp-food-prices | G14: Periodic | H14: Staple food prices in markets where WFP reporting exists | I14: Market-level | J14: Periodic | K14: Unknown | L14: Open | M14: Not started | N14: Not ingested | P14: Daniel | Q14: Cross-country dataset; confirm records for this country, dates, units and commodity coverage. | R14: Candidate lead from existing tracker; country/commodity coverage, latest observation, direct data endpoint and access method still require source-level verification. | S14: Candidate - not independently verified | T14: OpenTrace Africa
A15: North Africa | B15: Libya | C15: 1 | D15: Libya National Food Market / Price Reporting Source | E15: Market Information System | F15: https://www.fao.org/giews/food-prices/tool/public/#/home | G15: Periodic | H15: Staple grains, cereals and selected food commodities | I15: Market-level | J15: Periodic | K15: Unknown | L15: Open | M15: Not started | N15: Not ingested | P15: Daniel | Q15: Use FAO FPMA to check country/market coverage; this is not proof of a national live feed. | R15: Candidate lead from existing tracker; country/commodity coverage, latest observation, direct data endpoint and access method still require source-level verification. | S15: Candidate - not independently verified | T15: OpenTrace Africa
A16: North Africa | B16: Libya | C16: 2 | D16: Bureau of Statistics and Census | E16: Statistics Office | F16: https://bsc.ly | G16: Historical only | H16: Consumer food prices, CPI and food price indices | I16: National | J16: Monthly | K16: Unknown | L16: Open | M16: Not started | N16: Not ingested | P16: Daniel | Q16: Official institution landing page; locate a direct price table and confirm commodity-level data. | R16: Candidate lead from existing tracker; country/commodity coverage, latest observation, direct data endpoint and access method still require source-level verification. | S16: Candidate - not independently verified | T16: OpenTrace Africa
... A274: Southern Africa | B274: Zimbabwe | C274: 5 | D274: WFP / HDX Food Prices Dataset | E274: Multilateral / UN | F274: https://data.humdata.org/dataset/wfp-food-prices | G274: Periodic | H274: Staple food prices in markets where WFP reporting exists | I274: Market-level | J274: Periodic | K274: Unknown | L274: Open | M274: Not started | N274: Not ingested | P274: Daniel | Q274: Cross-country dataset; confirm records for this country, dates, units and commodity coverage. | R274: Candidate lead from existing tracker; country/commodity coverage, latest observation, direct data endpoint and access method still require source-level verification. | S274: Candidate - not independently verified | T274: OpenTrace Africa

Sheet Summary
A1: Progress Summary
A2: Candidate leads are listed for all 54 countries. Verified-source counts remain zero until evidence status is changed after source-level checks.
A4: By region
A5: Region | B5: Countries | C5: Target Sources | D5: Candidate Leads Listed | E5: API Available | F5: Accessed or Downloaded | G5: Ingested | H5: % Candidate Leads Listed | I5: % Ingested | J5: Verified Sources
A6: North Africa | B6: 6 | C6: =B6*5 -> 30 | D6: =COUNTIFS('Pricing Tracker'!$A$5:$A$274,$A6,'Pricing Tracker'!$D$5:$D$274,"<>") -> 30 | E6: =COUNTIFS('Pricing Tracker'!$A$5:$A$274,$A6,'Pricing Tracker'!$K$5:$K$274,"Yes") -> 0 | F6: =COUNTIFS('Pricing Tracker'!$A$5:$A$274,$A6,'Pricing Tracker'!$M$5:$M$274,"Accessed")+COUNTIFS('Pricing Tracker'!$A$5:$A$274,$A6,'Pricing Tracker'!$M$5:$M$274,"Downloaded") -> 0 | G6: =COUNTIFS('Pricing Tracker'!$A$5:$A$274,$A6,'Pricing Tracker'!$N$5:$N$274,"Ingested") -> 0 | H6: =IF(C6=0,0,D6/C6) -> 1 | I6: =IF(C6=0,0,G6/C6) -> 0 | J6: =COUNTIFS('Pricing Tracker'!$A$5:$A$274,$A6,'Pricing Tracker'!$S$5:$S$274,"Verified*") -> 0
A7: West Africa | B7: 15 | C7: =B7*5 -> 75 | D7: =COUNTIFS('Pricing Tracker'!$A$5:$A$274,$A7,'Pricing Tracker'!$D$5:$D$274,"<>") -> 75 | E7: =COUNTIFS('Pricing Tracker'!$A$5:$A$274,$A7,'Pricing Tracker'!$K$5:$K$274,"Yes") -> 0 | F7: =COUNTIFS('Pricing Tracker'!$A$5:$A$274,$A7,'Pricing Tracker'!$M$5:$M$274,"Accessed")+COUNTIFS('Pricing Tracker'!$A$5:$A$274,$A7,'Pricing Tracker'!$M$5:$M$274,"Downloaded") -> 0 | G7: =COUNTIFS('Pricing Tracker'!$A$5:$A$274,$A7,'Pricing Tracker'!$N$5:$N$274,"Ingested") -> 0 | H7: =IF(C7=0,0,D7/C7) -> 1 | I7: =IF(C7=0,0,G7/C7) -> 0 | J7: =COUNTIFS('Pricing Tracker'!$A$5:$A$274,$A7,'Pricing Tracker'!$S$5:$S$274,"Verified*") -> 0
A8: Central Africa | B8: 9 | C8: =B8*5 -> 45 | D8: =COUNTIFS('Pricing Tracker'!$A$5:$A$274,$A8,'Pricing Tracker'!$D$5:$D$274,"<>") -> 45 | E8: =COUNTIFS('Pricing Tracker'!$A$5:$A$274,$A8,'Pricing Tracker'!$K$5:$K$274,"Yes") -> 0 | F8: =COUNTIFS('Pricing Tracker'!$A$5:$A$274,$A8,'Pricing Tracker'!$M$5:$M$274,"Accessed")+COUNTIFS('Pricing Tracker'!$A$5:$A$274,$A8,'Pricing Tracker'!$M$5:$M$274,"Downloaded") -> 0 | G8: =COUNTIFS('Pricing Tracker'!$A$5:$A$274,$A8,'Pricing Tracker'!$N$5:$N$274,"Ingested") -> 0 | H8: =IF(C8=0,0,D8/C8) -> 1 | I8: =IF(C8=0,0,G8/C8) -> 0 | J8: =COUNTIFS('Pricing Tracker'!$A$5:$A$274,$A8,'Pricing Tracker'!$S$5:$S$274,"Verified*") -> 0
A9: East Africa | B9: 14 | C9: =B9*5 -> 70 | D9: =COUNTIFS('Pricing Tracker'!$A$5:$A$274,$A9,'Pricing Tracker'!$D$5:$D$274,"<>") -> 70 | E9: =COUNTIFS('Pricing Tracker'!$A$5:$A$274,$A9,'Pricing Tracker'!$K$5:$K$274,"Yes") -> 0 | F9: =COUNTIFS('Pricing Tracker'!$A$5:$A$274,$A9,'Pricing Tracker'!$M$5:$M$274,"Accessed")+COUNTIFS('Pricing Tracker'!$A$5:$A$274,$A9,'Pricing Tracker'!$M$5:$M$274,"Downloaded") -> 0 | G9: =COUNTIFS('Pricing Tracker'!$A$5:$A$274,$A9,'Pricing Tracker'!$N$5:$N$274,"Ingested") -> 0 | H9: =IF(C9=0,0,D9/C9) -> 1 | I9: =IF(C9=0,0,G9/C9) -> 0 | J9: =COUNTIFS('Pricing Tracker'!$A$5:$A$274,$A9,'Pricing Tracker'!$S$5:$S$274,"Verified*") -> 0
A10: Southern Africa | B10: 10 | C10: =B10*5 -> 50 | D10: =COUNTIFS('Pricing Tracker'!$A$5:$A$274,$A10,'Pricing Tracker'!$D$5:$D$274,"<>") -> 50 | E10: =COUNTIFS('Pricing Tracker'!$A$5:$A$274,$A10,'Pricing Tracker'!$K$5:$K$274,"Yes") -> 0 | F10: =COUNTIFS('Pricing Tracker'!$A$5:$A$274,$A10,'Pricing Tracker'!$M$5:$M$274,"Accessed")+COUNTIFS('Pricing Tracker'!$A$5:$A$274,$A10,'Pricing Tracker'!$M$5:$M$274,"Downloaded") -> 0 | G10: =COUNTIFS('Pricing Tracker'!$A$5:$A$274,$A10,'Pricing Tracker'!$N$5:$N$274,"Ingested") -> 0 | H10: =IF(C10=0,0,D10/C10) -> 1 | I10: =IF(C10=0,0,G10/C10) -> 0 | J10: =COUNTIFS('Pricing Tracker'!$A$5:$A$274,$A10,'Pricing Tracker'!$S$5:$S$274,"Verified*") -> 0
A11: Africa total | B11: =SUM(B6:B10) -> 54 | C11: =SUM(C6:C10) -> 270 | D11: =SUM(D6:D10) -> 270 | E11: =SUM(E6:E10) -> 0 | F11: =SUM(F6:F10) -> 0 | G11: =SUM(G6:G10) -> 0 | H11: =IF(C11=0,0,D11/C11) -> 1 | I11: =IF(C11=0,0,G11/C11) -> 0 | J11: =SUM(J6:J10) -> 0
A13: By country
A14: Region | B14: Country | C14: Candidate Leads Listed (of 5) | D14: API Available | E14: Accessed or Downloaded | F14: Ingested | G14: % Ingested of Target | H14: Last Checked (latest) | I14: Verified Sources
A15: North Africa | B15: Algeria | C15: =COUNTIFS('Pricing Tracker'!$B$5:$B$274,$B15,'Pricing Tracker'!$D$5:$D$274,"<>") -> 5 | D15: =COUNTIFS('Pricing Tracker'!$B$5:$B$274,$B15,'Pricing Tracker'!$K$5:$K$274,"Yes") -> 0 | E15: =COUNTIFS('Pricing Tracker'!$B$5:$B$274,$B15,'Pricing Tracker'!$M$5:$M$274,"Accessed")+COUNTIFS('Pricing Tracker'!$B$5:$B$274,$B15,'Pricing Tracker'!$M$5:$M$274,"Downloaded") -> 0 | F15: =COUNTIFS('Pricing Tracker'!$B$5:$B$274,$B15,'Pricing Tracker'!$N$5:$N$274,"Ingested") -> 0 | G15: =F15/5 -> 0 | H15: =IF(COUNTIFS('Pricing Tracker'!$B$5:$B$274,$B15,'Pricing Tracker'!$O$5:$O$274,">0")=0,"",SUMPRODUCT(MAX(('Pricing Tracker'!$B$5:$B$274=$B15)*'Pricing Tracker'!$O$5:$O$274))) | I15: =COUNTIFS('Pricing Tracker'!$B$5:$B$274,$B15,'Pricing Tracker'!$S$5:$S$274,"Verified*") -> 0
A16: North Africa | B16: Egypt | C16: =COUNTIFS('Pricing Tracker'!$B$5:$B$274,$B16,'Pricing Tracker'!$D$5:$D$274,"<>") -> 5 | D16: =COUNTIFS('Pricing Tracker'!$B$5:$B$274,$B16,'Pricing Tracker'!$K$5:$K$274,"Yes") -> 0 | E16: =COUNTIFS('Pricing Tracker'!$B$5:$B$274,$B16,'Pricing Tracker'!$M$5:$M$274,"Accessed")+COUNTIFS('Pricing Tracker'!$B$5:$B$274,$B16,'Pricing Tracker'!$M$5:$M$274,"Downloaded") -> 0 | F16: =COUNTIFS('Pricing Tracker'!$B$5:$B$274,$B16,'Pricing Tracker'!$N$5:$N$274,"Ingested") -> 0 | G16: =F16/5 -> 0 | H16: =IF(COUNTIFS('Pricing Tracker'!$B$5:$B$274,$B16,'Pricing Tracker'!$O$5:$O$274,">0")=0,"",SUMPRODUCT(MAX(('Pricing Tracker'!$B$5:$B$274=$B16)*'Pricing Tracker'!$O$5:$O$274))) | I16: =COUNTIFS('Pricing Tracker'!$B$5:$B$274,$B16,'Pricing Tracker'!$S$5:$S$274,"Verified*") -> 0
A17: North Africa | B17: Libya | C17: =COUNTIFS('Pricing Tracker'!$B$5:$B$274,$B17,'Pricing Tracker'!$D$5:$D$274,"<>") -> 5 | D17: =COUNTIFS('Pricing Tracker'!$B$5:$B$274,$B17,'Pricing Tracker'!$K$5:$K$274,"Yes") -> 0 | E17: =COUNTIFS('Pricing Tracker'!$B$5:$B$274,$B17,'Pricing Tracker'!$M$5:$M$274,"Accessed")+COUNTIFS('Pricing Tracker'!$B$5:$B$274,$B17,'Pricing Tracker'!$M$5:$M$274,"Downloaded") -> 0 | F17: =COUNTIFS('Pricing Tracker'!$B$5:$B$274,$B17,'Pricing Tracker'!$N$5:$N$274,"Ingested") -> 0 | G17: =F17/5 -> 0 | H17: =IF(COUNTIFS('Pricing Tracker'!$B$5:$B$274,$B17,'Pricing Tracker'!$O$5:$O$274,">0")=0,"",SUMPRODUCT(MAX(('Pricing Tracker'!$B$5:$B$274=$B17)*'Pricing Tracker'!$O$5:$O$274))) | I17: =COUNTIFS('Pricing Tracker'!$B$5:$B$274,$B17,'Pricing Tracker'!$S$5:$S$274,"Verified*") -> 0
A18: North Africa | B18: Mauritania | C18: =COUNTIFS('Pricing Tracker'!$B$5:$B$274,$B18,'Pricing Tracker'!$D$5:$D$274,"<>") -> 5 | D18: =COUNTIFS('Pricing Tracker'!$B$5:$B$274,$B18,'Pricing Tracker'!$K$5:$K$274,"Yes") -> 0 | E18: =COUNTIFS('Pricing Tracker'!$B$5:$B$274,$B18,'Pricing Tracker'!$M$5:$M$274,"Accessed")+COUNTIFS('Pricing Tracker'!$B$5:$B$274,$B18,'Pricing Tracker'!$M$5:$M$274,"Downloaded") -> 0 | F18: =COUNTIFS('Pricing Tracker'!$B$5:$B$274,$B18,'Pricing Tracker'!$N$5:$N$274,"Ingested") -> 0 | G18: =F18/5 -> 0 | H18: =IF(COUNTIFS('Pricing Tracker'!$B$5:$B$274,$B18,'Pricing Tracker'!$O$5:$O$274,">0")=0,"",SUMPRODUCT(MAX(('Pricing Tracker'!$B$5:$B$274=$B18)*'Pricing Tracker'!$O$5:$O$274))) | I18: =COUNTIFS('Pricing Tracker'!$B$5:$B$274,$B18,'Pricing Tracker'!$S$5:$S$274,"Verified*") -> 0
A19: North Africa | B19: Morocco | C19: =COUNTIFS('Pricing Tracker'!$B$5:$B$274,$B19,'Pricing Tracker'!$D$5:$D$274,"<>") -> 5 | D19: =COUNTIFS('Pricing Tracker'!$B$5:$B$274,$B19,'Pricing Tracker'!$K$5:$K$274,"Yes") -> 0 | E19: =COUNTIFS('Pricing Tracker'!$B$5:$B$274,$B19,'Pricing Tracker'!$M$5:$M$274,"Accessed")+COUNTIFS('Pricing Tracker'!$B$5:$B$274,$B19,'Pricing Tracker'!$M$5:$M$274,"Downloaded") -> 0 | F19: =COUNTIFS('Pricing Tracker'!$B$5:$B$274,$B19,'Pricing Tracker'!$N$5:$N$274,"Ingested") -> 0 | G19: =F19/5 -> 0 | H19: =IF(COUNTIFS('Pricing Tracker'!$B$5:$B$274,$B19,'Pricing Tracker'!$O$5:$O$274,">0")=0,"",SUMPRODUCT(MAX(('Pricing Tracker'!$B$5:$B$274=$B19)*'Pricing Tracker'!$O$5:$O$274))) | I19: =COUNTIFS('Pricing Tracker'!$B$5:$B$274,$B19,'Pricing Tracker'!$S$5:$S$274,"Verified*") -> 0
A20: North Africa | B20: Tunisia | C20: =COUNTIFS('Pricing Tracker'!$B$5:$B$274,$B20,'Pricing Tracker'!$D$5:$D$274,"<>") -> 5 | D20: =COUNTIFS('Pricing Tracker'!$B$5:$B$274,$B20,'Pricing Tracker'!$K$5:$K$274,"Yes") -> 0 | E20: =COUNTIFS('Pricing Tracker'!$B$5:$B$274,$B20,'Pricing Tracker'!$M$5:$M$274,"Accessed")+COUNTIFS('Pricing Tracker'!$B$5:$B$274,$B20,'Pricing Tracker'!$M$5:$M$274,"Downloaded") -> 0 | F20: =COUNTIFS('Pricing Tracker'!$B$5:$B$274,$B20,'Pricing Tracker'!$N$5:$N$274,"Ingested") -> 0 | G20: =F20/5 -> 0 | H20: =IF(COUNTIFS('Pricing Tracker'!$B$5:$B$274,$B20,'Pricing Tracker'!$O$5:$O$274,">0")=0,"",SUMPRODUCT(MAX(('Pricing Tracker'!$B$5:$B$274=$B20)*'Pricing Tracker'!$O$5:$O$274))) | I20: =COUNTIFS('Pricing Tracker'!$B$5:$B$274,$B20,'Pricing Tracker'!$S$5:$S$274,"Verified*") -> 0
A21: West Africa | B21: Benin | C21: =COUNTIFS('Pricing Tracker'!$B$5:$B$274,$B21,'Pricing Tracker'!$D$5:$D$274,"<>") -> 5 | D21: =COUNTIFS('Pricing Tracker'!$B$5:$B$274,$B21,'Pricing Tracker'!$K$5:$K$274,"Yes") -> 0 | E21: =COUNTIFS('Pricing Tracker'!$B$5:$B$274,$B21,'Pricing Tracker'!$M$5:$M$274,"Accessed")+COUNTIFS('Pricing Tracker'!$B$5:$B$274,$B21,'Pricing Tracker'!$M$5:$M$274,"Downloaded") -> 0 | F21: =COUNTIFS('Pricing Tracker'!$B$5:$B$274,$B21,'Pricing Tracker'!$N$5:$N$274,"Ingested") -> 0 | G21: =F21/5 -> 0 | H21: =IF(COUNTIFS('Pricing Tracker'!$B$5:$B$274,$B21,'Pricing Tracker'!$O$5:$O$274,">0")=0,"",SUMPRODUCT(MAX(('Pricing Tracker'!$B$5:$B$274=$B21)*'Pricing Tracker'!$O$5:$O$274))) | I21: =COUNTIFS('Pricing Tracker'!$B$5:$B$274,$B21,'Pricing Tracker'!$S$5:$S$274,"Verified*") -> 0
A22: West Africa | B22: Burkina Faso | C22: =COUNTIFS('Pricing Tracker'!$B$5:$B$274,$B22,'Pricing Tracker'!$D$5:$D$274,"<>") -> 5 | D22: =COUNTIFS('Pricing Tracker'!$B$5:$B$274,$B22,'Pricing Tracker'!$K$5:$K$274,"Yes") -> 0 | E22: =COUNTIFS('Pricing Tracker'!$B$5:$B$274,$B22,'Pricing Tracker'!$M$5:$M$274,"Accessed")+COUNTIFS('Pricing Tracker'!$B$5:$B$274,$B22,'Pricing Tracker'!$M$5:$M$274,"Downloaded") -> 0 | F22: =COUNTIFS('Pricing Tracker'!$B$5:$B$274,$B22,'Pricing Tracker'!$N$5:$N$274,"Ingested") -> 0 | G22: =F22/5 -> 0 | H22: =IF(COUNTIFS('Pricing Tracker'!$B$5:$B$274,$B22,'Pricing Tracker'!$O$5:$O$274,">0")=0,"",SUMPRODUCT(MAX(('Pricing Tracker'!$B$5:$B$274=$B22)*'Pricing Tracker'!$O$5:$O$274))) | I22: =COUNTIFS('Pricing Tracker'!$B$5:$B$274,$B22,'Pricing Tracker'!$S$5:$S$274,"Verified*") -> 0
A23: West Africa | B23: Cabo Verde | C23: =COUNTIFS('Pricing Tracker'!$B$5:$B$274,$B23,'Pricing Tracker'!$D$5:$D$274,"<>") -> 5 | D23: =COUNTIFS('Pricing Tracker'!$B$5:$B$274,$B23,'Pricing Tracker'!$K$5:$K$274,"Yes") -> 0 | E23: =COUNTIFS('Pricing Tracker'!$B$5:$B$274,$B23,'Pricing Tracker'!$M$5:$M$274,"Accessed")+COUNTIFS('Pricing Tracker'!$B$5:$B$274,$B23,'Pricing Tracker'!$M$5:$M$274,"Downloaded") -> 0 | F23: =COUNTIFS('Pricing Tracker'!$B$5:$B$274,$B23,'Pricing Tracker'!$N$5:$N$274,"Ingested") -> 0 | G23: =F23/5 -> 0 | H23: =IF(COUNTIFS('Pricing Tracker'!$B$5:$B$274,$B23,'Pricing Tracker'!$O$5:$O$274,">0")=0,"",SUMPRODUCT(MAX(('Pricing Tracker'!$B$5:$B$274=$B23)*'Pricing Tracker'!$O$5:$O$274))) | I23: =COUNTIFS('Pricing Tracker'!$B$5:$B$274,$B23,'Pricing Tracker'!$S$5:$S$274,"Verified*") -> 0
A24: West Africa | B24: Côte d'Ivoire | C24: =COUNTIFS('Pricing Tracker'!$B$5:$B$274,$B24,'Pricing Tracker'!$D$5:$D$274,"<>") -> 5 | D24: =COUNTIFS('Pricing Tracker'!$B$5:$B$274,$B24,'Pricing Tracker'!$K$5:$K$274,"Yes") -> 0 | E24: =COUNTIFS('Pricing Tracker'!$B$5:$B$274,$B24,'Pricing Tracker'!$M$5:$M$274,"Accessed")+COUNTIFS('Pricing Tracker'!$B$5:$B$274,$B24,'Pricing Tracker'!$M$5:$M$274,"Downloaded") -> 0 | F24: =COUNTIFS('Pricing Tracker'!$B$5:$B$274,$B24,'Pricing Tracker'!$N$5:$N$274,"Ingested") -> 0 | G24: =F24/5 -> 0 | H24: =IF(COUNTIFS('Pricing Tracker'!$B$5:$B$274,$B24,'Pricing Tracker'!$O$5:$O$274,">0")=0,"",SUMPRODUCT(MAX(('Pricing Tracker'!$B$5:$B$274=$B24)*'Pricing Tracker'!$O$5:$O$274))) | I24: =COUNTIFS('Pricing Tracker'!$B$5:$B$274,$B24,'Pricing Tracker'!$S$5:$S$274,"Verified*") -> 0
A25: West Africa | B25: The Gambia | C25: =COUNTIFS('Pricing Tracker'!$B$5:$B$274,$B25,'Pricing Tracker'!$D$5:$D$274,"<>") -> 5 | D25: =COUNTIFS('Pricing Tracker'!$B$5:$B$274,$B25,'Pricing Tracker'!$K$5:$K$274,"Yes") -> 0 | E25: =COUNTIFS('Pricing Tracker'!$B$5:$B$274,$B25,'Pricing Tracker'!$M$5:$M$274,"Accessed")+COUNTIFS('Pricing Tracker'!$B$5:$B$274,$B25,'Pricing Tracker'!$M$5:$M$274,"Downloaded") -> 0 | F25: =COUNTIFS('Pricing Tracker'!$B$5:$B$274,$B25,'Pricing Tracker'!$N$5:$N$274,"Ingested") -> 0 | G25: =F25/5 -> 0 | H25: =IF(COUNTIFS('Pricing Tracker'!$B$5:$B$274,$B25,'Pricing Tracker'!$O$5:$O$274,">0")=0,"",SUMPRODUCT(MAX(('Pricing Tracker'!$B$5:$B$274=$B25)*'Pricing Tracker'!$O$5:$O$274))) | I25: =COUNTIFS('Pricing Tracker'!$B$5:$B$274,$B25,'Pricing Tracker'!$S$5:$S$274,"Verified*") -> 0
A26: West Africa | B26: Ghana | C26: =COUNTIFS('Pricing Tracker'!$B$5:$B$274,$B26,'Pricing Tracker'!$D$5:$D$274,"<>") -> 5 | D26: =COUNTIFS('Pricing Tracker'!$B$5:$B$274,$B26,'Pricing Tracker'!$K$5:$K$274,"Yes") -> 0 | E26: =COUNTIFS('Pricing Tracker'!$B$5:$B$274,$B26,'Pricing Tracker'!$M$5:$M$274,"Accessed")+COUNTIFS('Pricing Tracker'!$B$5:$B$274,$B26,'Pricing Tracker'!$M$5:$M$274,"Downloaded") -> 0 | F26: =COUNTIFS('Pricing Tracker'!$B$5:$B$274,$B26,'Pricing Tracker'!$N$5:$N$274,"Ingested") -> 0 | G26: =F26/5 -> 0 | H26: =IF(COUNTIFS('Pricing Tracker'!$B$5:$B$274,$B26,'Pricing Tracker'!$O$5:$O$274,">0")=0,"",SUMPRODUCT(MAX(('Pricing Tracker'!$B$5:$B$274=$B26)*'Pricing Tracker'!$O$5:$O$274))) | I26: =COUNTIFS('Pricing Tracker'!$B$5:$B$274,$B26,'Pricing Tracker'!$S$5:$S$274,"Verified*") -> 0
... A68: Southern Africa | B68: Zimbabwe | C68: =COUNTIFS('Pricing Tracker'!$B$5:$B$274,$B68,'Pricing Tracker'!$D$5:$D$274,"<>") -> 5 | D68: =COUNTIFS('Pricing Tracker'!$B$5:$B$274,$B68,'Pricing Tracker'!$K$5:$K$274,"Yes") -> 0 | E68: =COUNTIFS('Pricing Tracker'!$B$5:$B$274,$B68,'Pricing Tracker'!$M$5:$M$274,"Accessed")+COUNTIFS('Pricing Tracker'!$B$5:$B$274,$B68,'Pricing Tracker'!$M$5:$M$274,"Downloaded") -> 0 | F68: =COUNTIFS('Pricing Tracker'!$B$5:$B$274,$B68,'Pricing Tracker'!$N$5:$N$274,"Ingested") -> 0 | G68: =F68/5 -> 0 | H68: =IF(COUNTIFS('Pricing Tracker'!$B$5:$B$274,$B68,'Pricing Tracker'!$O$5:$O$274,">0")=0,"",SUMPRODUCT(MAX(('Pricing Tracker'!$B$5:$B$274=$B68)*'Pricing Tracker'!$O$5:$O$274))) | I68: =COUNTIFS('Pricing Tracker'!$B$5:$B$274,$B68,'Pricing Tracker'!$S$5:$S$274,"Verified*") -> 0

Sheet Lists
A1: Organisation Type | B1: Data Type | C1: Geographic Level | D1: Update Frequency | E1: API Available | F1: Access Possibility | G1: Access Status | H1: Ingestion Status
A2: Government / Ministry | B2: Live | C2: National | D2: Real-time | E2: Yes | F2: Open | G2: Not started | H2: Not ingested
A3: Market Information System | B3: 24-hr delayed | C3: Sub-national | D3: Daily | E3: No | F3: Free registration | G3: Accessed | H3: In progress
A4: Commodity Exchange | B4: Periodic | C4: Market-level | D4: Weekly | E4: Partial | F4: Paid | G4: Downloaded | H4: Ingested
A5: Statistics Office | B5: Historical only | C5: Regional | D5: Monthly | E5: Unknown | F5: Partnership needed
A6: Multilateral / UN | D6: Quarterly | F6: Not accessible
A7: Regional Body | D7: Irregular
A8: NGO / Research | D8: Unknown
A9: Private Platform
A10: Other

Sheet Start Here - Daniel
A1: Item | B1: Instructions / Current State
A2: Purpose | B2: Combined working tracker for A) OpenTrace Africa, B) Farm Lover partner use cases, and C) the integrated delivery sequence.
A3: Research owner | B3: Daniel
A4: What is populated | B4: OpenTrace has 54 countries × 5 ranked candidate leads = 270 slots. Farm Lover has a source register, four partner workstreams, an ingestion backlog and a research evidence log.
A5: Facts/Claims | B5: All 270 OpenTrace rows are not 270 verified, accessible live feeds. Many country-level portals still need direct table/file/API validation. Statuses are deliberately conservative. ( We need to verify as we work along)
A6: OpenTrace exit criteria | B6: For each row, capture direct endpoint; country/commodity coverage; latest observation date; frequency; geographic granularity; units/currency; API or file access; licence/access terms; sample file or request evidence; and ingestion status.
A7: Farm Lover Team Focuse | B7: Validate each source against the target use case, retain the downloaded source artifact, record table/page/sheet and units, normalize dates/markets/commodities, run data-quality checks, then load into landing/Bronze/Silver/Gold layers.
A8: Important source distinction/Requirments? | B8: Farmgate/producer prices, market wholesale prices, retail food prices, export values and international benchmark prices are different measures. Do not merge them into one undifferentiated price series.
A9: Roadmap document | B9: In progress to alaing with this implemetion plan.

Sheet Farm Lover Team Source Register
A1: Workstream | B1: Country/Region | C1: Partner need | D1: Source / organisation | E1: Target data | F1: Direct URL | G1: Format / access path | H1: Priority | I1: Evidence status | J1: Access status | K1: Proposed ingestion | L1: Caveats / next validation
A2: G1 | B2: South Africa | C2: KwaZulu-Natal vegetable farmers | D2: Department of Agriculture: Statistics on Fresh Produce Markets archive | E2: Market sales volumes, sales value, average price by market and commodity; not farmgate price | F2: https://www.nda.gov.za/index.php/publication/336-fresh-produce | G2: Archive + downloadable XLSX | H2: High | I2: Candidate / archive URL recorded; inspect files and exact table coverage | J2: Open / likely downloadable | K2: XLSX batch ingest | L2: Use for market context; do not label wholesale market prices as prices received by farmers.
A3: G1 | B3: South Africa | C3: KwaZulu-Natal vegetable farmers | D3: Stats SA Agricultural Survey (P1101) | E3: Agricultural area/production and selected farming statistics; check vegetable/provincial detail | F3: https://www.statssa.gov.za/?PPN=P1101&page_id=1854 | G3: Published report/tables | H3: Medium | I3: Candidate / direct report landing page identified; table coverage needs validation | J3: Open / publication access | K3: PDF/XLSX extraction | L3: Record survey year, province, crop, unit and page/table.
A4: G1 | B4: South Africa | C4: KwaZulu-Natal vegetable farmers | D4: FAOSTAT Producer Prices | E4: National annual/monthly producer prices where available, plus metadata | F4: https://www.fao.org/faostat/en/#data | G4: API/bulk download | H4: Medium | I4: Global portal confirmed; South Africa × target crop coverage still needs checking | J4: Open | K4: API/bulk download | L4: Benchmark only if crop/period/definition aligns; national series may not be provincial.
A5: G2 | B5: South Africa | C5: Gauteng vegetable traders | D5: Statistics on Fresh Produce Markets 2024 XLSX | E5: Market-level volumes, sales values and average prices; includes market tables to inspect | F5: https://www.nda.gov.za/images/Branches/Economica%20Development%20Trade%20and%20Marketing/Statistc%20and%20%20Economic%20Analysis/statistical-information/statistics-on-fresh-produce-markets-2024.xlsx | G5: XLSX | H5: High | I5: Direct XLSX URL from plan; current reachability not re-tested in this pass | J5: Open / verify download | K5: XLSX batch ingest | L5: Preferred initial MVP. Preserve market, commodity, date/year, volume and sales-value definitions.
A6: G2 | B6: South Africa | C6: Gauteng vegetable traders | D6: Joburg Market daily prices | E6: Daily wholesale prices and market information | F6: https://joburgmarket.co.za/jhb-market/dailyprices.php | G6: Web page / possible structured data | H6: High | I6: Portal URL recorded; structured export/API and history need validation | J6: Open / validation pending | K6: Download if supported; otherwise approved manual extraction only | L6: Do not assume an API exists; inspect page/network/export and terms.
A7: G2 | B7: South Africa | C7: Gauteng vegetable traders | D7: Fresh Produce Markets archive | E7: Historical market workbooks for trend series | F7: https://www.nda.gov.za/index.php/publication/336-fresh-produce | G7: Archive + XLSX | H7: High | I7: Archive URL recorded; select relevant years and verify columns | J7: Open / likely downloadable | K7: XLSX batch ingest | L7: Potentially supports broader markets, not only Johannesburg.
A8: G3 | B8: Nigeria | C8: Abuja/FCT, Edo, Benue, Delta | D8: WFP Food Prices for Nigeria via HDX | E8: Physical food prices by date, state/admin1, market, commodity, unit, currency and price type | F8: https://data.humdata.org/dataset/42db041f-7aaf-4ab4-961f-2a12096861e7 | G8: CSV dataset | H8: High | I8: Prior workbook records a successful CSV sample pull; target-state freshness/coverage still needs a fresh filter test | J8: Public CSV / verify current resource | K8: CSV batch ingest | L8: Validate FCT, Edo, Benue and Delta individually; keep stale commodities flagged.
A9: G3 | B9: Nigeria | C9: Abuja/FCT, Edo, Benue, Delta | D9: NBS Selected Food Price Watch related materials | E9: Official food-price reports and downloadable tables | F9: https://microdata.nigerianstat.gov.ng/index.php/catalog/162/related-materials | G9: Reports / ZIP / XLSX | H9: High | I9: Prior research notes public report downloads; current files and geographic coverage need verification | J9: Public downloads / validate | K9: ZIP/XLSX ingestion | L9: Record month, state coverage, commodity, unit and price type.
A10: G3 | B10: Nigeria | C10: Abuja/FCT, Edo, Benue, Delta | D10: NBS Nigeria Agricultural Survey catalogue | E10: Agricultural production and survey data where released | F10: https://microdata.nigerianstat.gov.ng/index.php/catalog/173 | G10: Catalogue / survey files | H10: Medium | I10: Catalogue identified; dataset access and state/crop variables need checking | J10: Catalogue open / file access pending | K10: Download after access review | L10: Not a substitute for market prices.
A11: G3 | B11: Nigeria | C11: Abuja/FCT, Edo, Benue, Delta | D11: World Bank Nigeria Real-Time Food Prices catalogue | E11: Market price panel; access may require microdata login depending on file | F11: https://microdata.worldbank.org/catalog/5712 | G11: Catalogue / API / files | H11: Medium | I11: Prior workbook indicates metadata and table API paths; downloadable microdata access may be gated | J11: Metadata/API route / verify licence | K11: API/table pull if permitted | L11: Validate target states and date freshness; keep access limitations documented.
A12: G3 | B12: Nigeria | C12: Abuja/FCT, Edo, Benue, Delta | D12: FAO GIEWS FPMA | E12: Domestic staple food prices where country/commodity series exist | F12: https://www.fao.org/giews/food-prices/en/ | G12: Portal / database | H12: Medium | I12: Global tool confirmed; target commodities, locations, and extraction route require checking | J12: Open / coverage pending | K12: API/export if documented | L12: Supplementary source; do not assume it covers every target state.
... A24: Nigeria | B24: Nigeria | C24: Tradeable commodity / physical exchange benchmark | D24: AFEX XIP | E24: Exchange/market information for covered Nigerian commodities | F24: https://xip.afex.africa/ | G24: Portal / account-dependent | H24: Medium | I24: Prior workbook indicates portal reachable but paid/account access may apply; no ingestion-ready API established | J24: Access/paid validation pending | K24: Only after access and terms review | L24: Do not block baseline pipeline on niche commodities such as sesame.

Sheet Partner Workstreams
A1: ID | B1: Geography | C1: Partner / audience | D1: Required data | E1: Priority source set | F1: Initial access method | G1: Priority | H1: Acceptance notes
A2: G1 | B2: KwaZulu-Natal, South Africa | C2: Vegetable farmers | D2: Vegetable production/area; available producer prices; relevant provincial/crop breakdowns | E2: Stats SA Agricultural Survey; FAOSTAT producer prices; fresh-produce market stats as contextual data | F2: Historical reports / API / XLSX | G2: High | H2: Separate producer/farmgate measures from wholesale market observations. Verify crop and province coverage before accepting a source.
A3: G2 | B3: Gauteng, South Africa | C3: Vegetable traders | D3: Wholesale prices, mass/quantity sold, sales value and market-level trends | E3: Stats on Fresh Produce Markets 2024 XLSX; archive; Joburg Market daily prices | F3: XLSX first, portal validation second | G3: High | H3: Preferred MVP: parse the official XLSX into long format; preserve metric definitions and market IDs/names.
A4: G3 | B4: Abuja/FCT, Edo, Benue, Delta, Nigeria | C4: Farmers / market stakeholders | D4: Food prices by commodity, market, date, unit, currency and price type; target-state coverage | E4: WFP/HDX CSV; NBS Selected Food Price Watch; World Bank RTPF; FAO FPMA as supplement | F4: CSV/XLSX/API depending on source | G4: High | H4: State-by-state coverage matrix required. Do not infer target-state availability from national dataset title.
A5: G4 | B5: Kenya | C5: Avocado and banana farmers/exporters | D5: Production, harvested area, yields, export volumes/values and market prices if available | E5: KNBS Economic Survey 2026; AFA Yearbooks 2025/2024; KAMIS; FAOSTAT | F5: PDF table extraction + portal validation + API/bulk | G5: High | H5: Export stats are not farmgate prices. Validate whether banana and avocado are separately reported and at what geography.
A6: Global benchmarks | B6: Global | C6: Cross-country comparisons / reference prices | D6: Monthly international benchmark prices, production/trade context and selected price series | E6: World Bank Pink Sheet; FAOSTAT; FAO FPMA; World Bank RTPF | F6: XLSX + API/bulk + source-specific tables | G6: High | H6: Keep benchmark, physical wholesale, retail, producer and export unit values in separate measure classes.

Sheet Ingestion Backlog
A1: Priority | B1: Workstream | C1: Task | D1: Deliverable / exit criteria | E1: Status | F1: Owner | G1: Notes | H1: Date
A2: P0 | B2: Scope and credentials | C2: Confirm GCP project, Cloud Storage bucket, BigQuery dataset, service account, secrets handling, billing and target users | D2: Environment checklist + access owner list | E2: Partaily confimed | F2: Daniel | G2: Cloud level
A3: P1 | B3: Project Source | C3: Start from the source code to ground up and Cloud | D3: Environment checklist + access owner list | E3: Intiaited postive progress | F3: Daniel | G3: Project setup (Source code level)
A4: P2 | B4: South Africa XLSX MVP | C4: Download and profile Statistics on Fresh Produce Markets 2024 workbook; inventory sheets/headers; identify market, commodity, period, sales quantity/value and price fields | D4: Source profile, raw file, parsing notebook/script, Bronze table | E4: High | F4: Daniel | G4: Do not assume one worksheet layout; inspect workbook before coding.
A5: P3 | B5: Nigeria WFP/HDX CSV | C5: Pull current CSV; inspect dates/markets/admin1/commodity/unit/price type; test Abuja/FCT, Edo, Benue and Delta separately; quantify stale series | D5: Source snapshot + state coverage report + Bronze table | E5: High | F5: Daniel | G5: Source snapshot indicates some commodity series can be stale; preserve observation date and freshness flags.
A6: P4 | B6: Kenya annual statistics | C6: Download KNBS and AFA reports; record exact page/table, crop, year, units and geography; extract avocado/banana data | D6: Traceable annual fact tables and source-page metadata | E6: High | F6: Daniel | G6: Keep exports, production, and price metrics distinct.
A7: P5 | B7: KAMIS access gate | C7: Test search/filter, historical data, avocado/banana coverage, units, downloadable files/API, terms and latest observation | D7: Access decision record and sample extract if permitted | E7: High | F7: Daniel | G7: Do not claim API or scrape the portal without evidence and terms review.
A8: P6 | B8: Global benchmarks | C8: Load World Bank Pink Sheet monthly XLSX and selected FAOSTAT domains; retain release/version metadata | D8: Benchmark tables in Bronze/Silver | E8: High | F8: Daniel | G8: Paid. I am not paying for live API until a live series is a stated requirement.
A9: P7 | B9: OpenTrace source verification | C9: For each of 270 candidate slots, verify direct endpoint, country/commodity coverage, latest date, frequency, units, access/licence and sample extraction | D9: Evidence-backed 54-country tracker; mark genuine gaps explicitly | E9: High | F9: Daniel | G9: The five slots are candidates, not an instruction to invent five usable feeds when fewer exist.
A10: P8 | B10: Canonical data model | C10: Define price observation, production observation, trade observation, market sales observation; source ID, geography, commodity IDs, units, currencies, date semantics | D10: Schema and mapping tables | E10: High | F10: Daniel | G10: Avoid mixing local currency/units or price stages without explicit conversion metadata.
A11: P9 | B11: Quality and operations | C11: Add idempotency, source freshness checks, schema drift alerts, duplicate handling, row counts, parse failures and run logs | D11: Repeatable scheduled ingestion + monitoring | E11: High | F11: Daniel | G11: Keep raw source files immutable in landing storage.
A12: P10 | B12: Gold outputs and handover | C12: Create partner-specific views, data dictionary, source lineage, known gaps and refresh schedule | D12: Consumer-ready views + runbook | E12: Medium | F12: Daniel | G12: Only expose measures that pass the source/quality acceptance criteria.

Sheet Research Evidence Log
A1: Evidence date | B1: Source / claim | C1: URL | D1: What the evidence supports | E1: Evidence basis | F1: Verification status | G1: Limitations
A2: 2026-10-19 | B2: FAO prices overview | C2: https://www.fao.org/prices/en | D2: FAO describes domestic producer prices and consumer price indices from FAOSTAT, plus wholesale/retail prices from FPMA and international prices/indices. | E2: Official FAO prices overview found in current web search. | F2: Verified at overview level; not country/crop-specific. | G2: Does not prove every African country has every commodity/market series.
A3: 2026-10-19 | B3: FAOSTAT portal | C3: https://faostat.fao.org/ | D3: FAOSTAT says it provides free agriculture data for over 245 countries and territories and has an API developer portal and bulk downloads; producer prices had a database update shown for 2026-10-09. | E3: Official FAOSTAT portal found in current web search. | F3: Verified at portal level; individual dataset queries still required. | G3: Country coverage is not equivalent to price coverage for a specific crop and frequency.
A4: 2026-10-19 | B4: FAO FPMA page | C4: https://www.fao.org/giews/food-prices/en/ | D4: FAO describes FPMA as domestic food price information and lists coverage of over 90 countries in the price overview. | E4: Official FAO page found in current web search. | F4: Verified at overview level; source-specific extract method pending. | G4: Do not claim API availability without confirming documented access.
A5: 2026-10-19 | B5: Farm Lover source workbook | C5: https://data.humdata.org/dataset/42db041f-7aaf-4ab4-961f-2a12096861e7 | D5: The provided Farm Lover workbook records a previous successful CSV sample pull for WFP Nigeria food prices and a prior sample for the World Bank Pink Sheet XLSX. | E5: Evidence recorded in supplied workbook; not freshly re-pulled in this pass. | F5: Previously sample-pulled per supplied workbook; current run/target state freshness pending. | G5: Verify resource still live and target-state coverage before production ingestion.
A6: 2026-10-19 | B6: OpenTrace tracker status | C6: https://www.fao.org/giews/food-prices/tool/public/#/home | D6: Existing tracker workbook contains 54 country groups × five ranked candidate source slots; its own notes repeatedly call for coverage/access verification. | E6: Existing spreadsheet inspected. | F6: Candidate coverage scaffold exists; not 270 verified feeds. | G6: Blank Last Checked fields are intentional until each exact row is checked.
